image_format_converter_mcp/__init__.py
image_format_converter_mcp/__main__.py
image_format_converter_mcp/general_conversion.py
image_format_converter_mcp/gif_conversion.py
image_format_converter_mcp/pdf_conversion.py
image_format_converter_mcp-0.2.3.dist-info/METADATA
image_format_converter_mcp-0.2.3.dist-info/WHEEL
image_format_converter_mcp-0.2.3.dist-info/entry_points.txt
image_format_converter_mcp-0.2.3.dist-info/licenses/LICENSE
image_format_converter_mcp-0.2.3.dist-info/RECORD
