Metadata-Version: 2.4
Name: image-format-converter-mcp
Version: 0.2.3
Summary: Model Context Protocol Server for Image File Format Conversion
Project-URL: Homepage, https://github.com/Beta0415/image-convertor-mcp
Project-URL: Repository, https://github.com/Beta0415/image-convertor-mcp
Project-URL: Documentation, https://github.com/Beta0415/image-convertor-mcp#readme
Project-URL: Issues, https://github.com/Beta0415/image-convertor-mcp/issues
Author: Beta
Maintainer: Beta
License: MIT License
License-File: LICENSE
Keywords: gif,image-conversion,image-processing,mcp,model-context-protocol,pdf
Classifier: Development Status :: 4 - Beta
Classifier: Intended Audience :: Developers
Classifier: License :: OSI Approved :: MIT License
Classifier: Operating System :: OS Independent
Classifier: Programming Language :: Python :: 3
Classifier: Programming Language :: Python :: 3.10
Classifier: Programming Language :: Python :: 3.11
Classifier: Programming Language :: Python :: 3.12
Classifier: Topic :: Multimedia :: Graphics :: Graphics Conversion
Classifier: Topic :: Scientific/Engineering :: Image Processing
Classifier: Topic :: Software Development :: Libraries :: Python Modules
Requires-Python: >=3.10
Requires-Dist: mcp>=0.1.0
Requires-Dist: pillow-heif>=0.15.0
Requires-Dist: pillow>=10.0.0
Requires-Dist: pymupdf>=1.24.0
